commoncast/__init__.py
commoncast/chromecast/__init__.py
commoncast/chromecast/adapter.py
commoncast/cli/cc_discover.py
commoncast/event.py
commoncast/py.typed
commoncast/registry.py
commoncast/server.py
commoncast/types.py
commoncast-0.1.0.dist-info/licenses/LICENSE
commoncast-0.1.0.dist-info/WHEEL
commoncast-0.1.0.dist-info/entry_points.txt
commoncast-0.1.0.dist-info/METADATA
commoncast-0.1.0.dist-info/RECORD
