Metadata-Version: 2.4
Name: CommonCast
Version: 0.1.0
Summary: A unified API for casting images to devices
Author: John Strunk
Author-email: John Strunk <john.strunk@gmail.com>
License-Expression: LGPL-3.0-only
License-File: LICENSE
Classifier: Development Status :: 1 - Planning
Classifier: Intended Audience :: Developers
Classifier: License :: OSI Approved :: GNU Lesser General Public License v3 (LGPLv3)
Classifier: Operating System :: OS Independent
Classifier: Programming Language :: Python :: 3 :: Only
Classifier: Topic :: Multimedia :: Graphics :: Presentation
Classifier: Topic :: Software Development :: Libraries :: Python Modules
Classifier: Typing :: Typed
Requires-Dist: aiohttp==3.13.2
Requires-Dist: pychromecast==13.1.0
Requires-Python: >=3.10
Project-URL: Homepage, https://github.com/JohnStrunk/CommonCast
